chatbot/__init__.py
chatbot/constants.py
chatbot/mapper.py
chatbot/version.py
chatbot/local/de/default.template
chatbot/local/de/substitutions.json
chatbot/local/de/words.txt
chatbot/local/en/default.template
chatbot/local/en/substitutions.json
chatbot/local/en/words.txt
chatbot/local/he/default.template
chatbot/local/he/substitutions.json
chatbot/local/he/words.txt
chatbot/local/pt-br/default.template
chatbot/local/pt-br/substitutions.json
chatbot/local/pt-br/words.txt
chatbot/media/robot.png
chatbot/media/send.png
chatbot/media/user.png
chatbot/spellcheck/__init__.py
chatbot/substitution/__init__.py
chatbotAI-0.3.1.2.dist-info/LICENSE
chatbotAI-0.3.1.2.dist-info/METADATA
chatbotAI-0.3.1.2.dist-info/WHEEL
chatbotAI-0.3.1.2.dist-info/top_level.txt
chatbotAI-0.3.1.2.dist-info/RECORD
